weblinks/__init__.py
weblinks/config.py
weblinks/proxy.py
weblinks/run.py
weblinks/utils.py
weblinks/weblinks.py
weblinks-2.0.dist-info/LICENSE
weblinks-2.0.dist-info/METADATA
weblinks-2.0.dist-info/WHEEL
weblinks-2.0.dist-info/entry_points.txt
weblinks-2.0.dist-info/top_level.txt
weblinks-2.0.dist-info/RECORD
