Metadata-Version: 2.1
Name: weblinks
Version: 2.0
Summary: Wanted to fetch the links from web and filter them using substring, a file extentions
Home-page: https://github.com/kirankotari/weblinks
Author: Kiran Kumar Kotari
Author-email: kirankotari@live.com
License: UNKNOWN
Keywords: weblinks getlinks web-links get-links fetch-links filter-links filterlinks
Platform: UNKNOWN
Classifier: Development Status :: 5 - Production/Stable
Classifier: Intended Audience :: Developers
Classifier: Topic :: Software Development :: Build Tools
Classifier: License :: OSI Approved :: Apache Software License
Classifier: Programming Language :: Python :: 3
Classifier: Operating System :: OS Independent
License-File: LICENSE
Requires-Dist: validators (>=0.18.2)
